AUTHORS.rst
CONTRIBUTING.rst
HISTORY.rst
LICENSE
MANIFEST.in
README.rst
setup.cfg
setup.py
docs/Makefile
docs/authors.rst
docs/conf.py
docs/contributing.rst
docs/history.rst
docs/index.rst
docs/installation.rst
docs/make.bat
docs/readme.rst
docs/usage.rst
fastatools/__init__.py
fastatools/cli.py
fastatools/fastatools.py
fastatools.egg-info/PKG-INFO
fastatools.egg-info/SOURCES.txt
fastatools.egg-info/dependency_links.txt
fastatools.egg-info/entry_points.txt
fastatools.egg-info/not-zip-safe
fastatools.egg-info/requires.txt
fastatools.egg-info/top_level.txt
tests/__init__.py
tests/test_cli.py
tests/test_fastatools.py