Metadata-Version: 1.1
Name: fastatools
Version: 1.2.0
Summary: Tools for working with fasta files.
Home-page: https://github.com/CFSAN-Biostatistics/fastatools
Author: Steve Davis
Author-email: steven.davis@fda.hhs.gov
License: BSD
Keywords: bioinformatics,NGS,fastatools
Platform: UNKNOWN
Classifier: Development Status :: 4 - Beta
Classifier: Intended Audience :: Developers
Classifier: License :: OSI Approved :: BSD License
Classifier: Natural Language :: English
Classifier: Programming Language :: Python :: 2
Classifier: Programming Language :: Python :: 2.7
Classifier: Programming Language :: Python :: 3
Classifier: Programming Language :: Python :: 3.4
Classifier: Programming Language :: Python :: 3.5
Classifier: Programming Language :: Python :: 3.6
